.gitignore
CMakeLists.txt
LICENSE
MANIFEST.in
README.md
pyproject.toml
setup.py
.github/workflows/linux.yml
.github/workflows/windows.yml
cython/symp_basis.c
cython/symp_basis.pyx
dev/cython_test.py
dev/link-60819.log
dev/manifold-L8a20.log
dev/symplectic_basis_main.c
dev/symplectic_basis_test.c
dev/test_base.py
dev/test_linux.py
dev/test_windows.py
dev/CuspedCensusData/link-0.tri
dev/CuspedCensusData/link-1.tri
dev/CuspedCensusData/link-10.tri
dev/CuspedCensusData/link-11.tri
dev/CuspedCensusData/link-12.tri
dev/CuspedCensusData/link-13.tri
dev/CuspedCensusData/link-14.tri
dev/CuspedCensusData/link-15.tri
dev/CuspedCensusData/link-16.tri
dev/CuspedCensusData/link-17.tri
dev/CuspedCensusData/link-18.tri
dev/CuspedCensusData/link-19.tri
dev/CuspedCensusData/link-2.tri
dev/CuspedCensusData/link-20.tri
dev/CuspedCensusData/link-21.tri
dev/CuspedCensusData/link-3.tri
dev/CuspedCensusData/link-4.tri
dev/CuspedCensusData/link-5.tri
dev/CuspedCensusData/link-6.tri
dev/CuspedCensusData/link-7.tri
dev/CuspedCensusData/link-8.tri
dev/CuspedCensusData/link-9.tri
dev/CuspedCensusData/link-l8a20.tri
dev/CuspedCensusData/link-random.tri
dev/CuspedCensusData/terse5.bin
dev/CuspedCensusData/terse6n.bin
dev/CuspedCensusData/terse6o.bin
dev/CuspedCensusData/terse7n.bin
dev/CuspedCensusData/terse7o.bin
snappea_src/addl_code/addl_code.h
snappea_src/addl_code/braid.c
snappea_src/addl_code/change_peripheral_curves_nonorientable.c
snappea_src/addl_code/change_peripheral_curves_nonorientable.h
snappea_src/addl_code/choose_gen_helper.c
snappea_src/addl_code/combinatorial_bases.c
snappea_src/addl_code/dilog.c
snappea_src/addl_code/dilog.h
snappea_src/addl_code/get_gluing_equations.c
snappea_src/addl_code/gluing_equations_pgl.c
snappea_src/addl_code/gluing_equations_pgl.h
snappea_src/addl_code/isomorphism_signature.c
snappea_src/addl_code/isomorphism_signature.h
snappea_src/addl_code/ptolemy_equations.c
snappea_src/addl_code/ptolemy_equations.h
snappea_src/addl_code/ptolemy_types.c
symplectic_basis.egg-info/PKG-INFO
symplectic_basis.egg-info/SOURCES.txt
symplectic_basis.egg-info/dependency_links.txt
symplectic_basis.egg-info/top_level.txt
